parallelformers/__init__.py
parallelformers/parallelize.py
parallelformers/parallel/__init__.py
parallelformers/parallel/engine.py
parallelformers/parallel/process.py
parallelformers/parallel/replacing.py
parallelformers/parallel/slicing.py
parallelformers/policies/__init__.py
parallelformers/policies/albert.py
parallelformers/policies/bart.py
parallelformers/policies/bert.py
parallelformers/policies/bigbird.py
parallelformers/policies/bigbird_pegasus.py
parallelformers/policies/blenderbot.py
parallelformers/policies/blenderbot_small.py
parallelformers/policies/clip.py
parallelformers/policies/convbert.py
parallelformers/policies/ctrl.py
parallelformers/policies/deberta.py
parallelformers/policies/deberta_v2.py
parallelformers/policies/deit.py
parallelformers/policies/detr.py
parallelformers/policies/distil_bert.py
parallelformers/policies/electra.py
parallelformers/policies/fsmt.py
parallelformers/policies/funnel.py
parallelformers/policies/gpt2.py
parallelformers/policies/gpt_neo.py
parallelformers/policies/hubert.py
parallelformers/policies/ibert.py
parallelformers/policies/layoutlm.py
parallelformers/policies/led.py
parallelformers/policies/longformer.py
parallelformers/policies/luke.py
parallelformers/policies/lxmert.py
parallelformers/policies/m2m_100.py
parallelformers/policies/marian.py
parallelformers/policies/mbart.py
parallelformers/policies/mobilebert.py
parallelformers/policies/mpnet.py
parallelformers/policies/openai.py
parallelformers/policies/pegasus.py
parallelformers/policies/prophetnet.py
parallelformers/policies/reformer.py
parallelformers/policies/roberta.py
parallelformers/policies/roformer.py
parallelformers/policies/speech_to_text.py
parallelformers/policies/t5.py
parallelformers/policies/tapas.py
parallelformers/policies/transfo_xl.py
parallelformers/policies/visual_bert.py
parallelformers/policies/vit.py
parallelformers/policies/wav2vec.py
parallelformers/policies/xlm.py
parallelformers/policies/xlnet.py
parallelformers-1.0.1.dist-info/LICENSE
parallelformers-1.0.1.dist-info/LICENSE.3rd_party_library
parallelformers-1.0.1.dist-info/METADATA
parallelformers-1.0.1.dist-info/WHEEL
parallelformers-1.0.1.dist-info/top_level.txt
parallelformers-1.0.1.dist-info/RECORD
