Metadata-Version: 2.1
Name: parallelformers
Version: 1.0.1
Summary: An Efficient Model Parallelization Toolkit for Deployment
Home-page: https://github.com/tunib-ai/parallelformers
Author: TUNiB
Author-email: kevin.ko@tunib.ai
License: UNKNOWN
Platform: UNKNOWN
Classifier: Intended Audience :: Developers
Classifier: Intended Audience :: Science/Research
Classifier: Development Status :: 3 - Alpha
Classifier: License :: OSI Approved :: Apache Software License
Classifier: Programming Language :: Python :: 3
Classifier: Programming Language :: Python :: 3.6
Classifier: Programming Language :: Python :: 3.7
Classifier: Programming Language :: Python :: 3.8
Classifier: Programming Language :: Python :: 3.9
Classifier: Topic :: Scientific/Engineering :: Artificial Intelligence
Classifier: Topic :: Software Development :: Libraries
Requires-Python: >=3.6.0
Requires-Dist: transformers (>=4.2)
Requires-Dist: torch
Requires-Dist: dacite
Requires-Dist: dataclasses ; python_version < "3.7"
